flask_resty_tenants/__init__.py
flask_resty_tenants/authorization.py
Flask_RESTy_Tenants-0.8.0.dist-info/LICENSE
Flask_RESTy_Tenants-0.8.0.dist-info/METADATA
Flask_RESTy_Tenants-0.8.0.dist-info/WHEEL
Flask_RESTy_Tenants-0.8.0.dist-info/top_level.txt
Flask_RESTy_Tenants-0.8.0.dist-info/RECORD
