Metadata-Version: 2.1
Name: Flask-RESTy-Tenants
Version: 0.8.0
Summary: Multitenant authorization for Flask-RESTy
Home-page: https://github.com/4Catalyzer/flask-resty-tenants
Author: Giacomo Tagliabue
Author-email: giacomo.tag@gmail.com
License: MIT
Keywords: rest flask multitenancy
Platform: UNKNOWN
Classifier: Development Status :: 3 - Alpha
Classifier: Framework :: Flask
Classifier: Environment :: Web Environment
Classifier: Intended Audience :: Developers
Classifier: License :: OSI Approved :: MIT License
Classifier: Operating System :: OS Independent
Classifier: Programming Language :: Python
Classifier: Programming Language :: Python :: 3
Classifier: Programming Language :: Python :: 3.6
Classifier: Programming Language :: Python :: 3.7
Classifier: Programming Language :: Python :: 3.8
Classifier: Programming Language :: Python :: 3 :: Only
Requires-Python: >=3.6
Requires-Dist: Flask (>=0.10)
Requires-Dist: Flask-RESTy (>=0.13.0)
Requires-Dist: SQLAlchemy (>=1.0.0)
